odoo/addons/mail_partner_opt_out/README.rst
odoo/addons/mail_partner_opt_out/__init__.py
odoo/addons/mail_partner_opt_out/__manifest__.py
odoo/addons/mail_partner_opt_out/i18n/es.po
odoo/addons/mail_partner_opt_out/i18n/fr.po
odoo/addons/mail_partner_opt_out/i18n/it.po
odoo/addons/mail_partner_opt_out/i18n/mail_partner_opt_out.pot
odoo/addons/mail_partner_opt_out/models/__init__.py
odoo/addons/mail_partner_opt_out/models/mail_thread_blacklist.py
odoo/addons/mail_partner_opt_out/readme/CONTRIBUTORS.rst
odoo/addons/mail_partner_opt_out/readme/DESCRIPTION.rst
odoo/addons/mail_partner_opt_out/readme/USAGE.rst
odoo/addons/mail_partner_opt_out/static/description/icon.png
odoo/addons/mail_partner_opt_out/static/description/index.html
odoo/addons/mail_partner_opt_out/views/res_partner_views.xml
odoo14_addon_mail_partner_opt_out-14.0.1.0.1.dev10.dist-info/METADATA
odoo14_addon_mail_partner_opt_out-14.0.1.0.1.dev10.dist-info/WHEEL
odoo14_addon_mail_partner_opt_out-14.0.1.0.1.dev10.dist-info/top_level.txt
odoo14_addon_mail_partner_opt_out-14.0.1.0.1.dev10.dist-info/RECORD
