Metadata-Version: 2.1
Name: odoo14-addon-mail_partner_opt_out
Version: 14.0.1.0.1.dev10
Summary: Add the partner's email to the blackmailed list
Home-page: https://github.com/OCA/social
Author: ForgeFlow, Odoo Community Association (OCA)
Author-email: support@odoo-community.org
License: LGPL-3
Classifier: Programming Language :: Python
Classifier: Framework :: Odoo
Classifier: Framework :: Odoo :: 14.0
Classifier: License :: OSI Approved :: GNU Lesser General Public License v3 (LGPLv3)
Classifier: Development Status :: 4 - Beta
Requires-Python: >=3.6
Requires-Dist: odoo<14.1dev,>=14.0a
